take_it_easy/__init__.py
take_it_easy/_modidx.py
take_it_easy/board.py
take_it_easy/play.py
take_it_easy/tiles.py
take_it_easy-0.0.3.dist-info/LICENSE
take_it_easy-0.0.3.dist-info/METADATA
take_it_easy-0.0.3.dist-info/WHEEL
take_it_easy-0.0.3.dist-info/entry_points.txt
take_it_easy-0.0.3.dist-info/top_level.txt
take_it_easy-0.0.3.dist-info/RECORD
