Metadata-Version: 2.1
Name: take-it-easy
Version: 0.0.3
Summary: An implementation of the popular board game Take It Easy! to be used for Reinforcement Learning
Home-page: https://github.com/majoma7/take_it_easy
Author: Magnus Maichle
Author-email: magnus.maichle@uni-wuerzburg.de
License: Apache Software License 2.0
Keywords: nbdev jupyter notebook python
Classifier: Development Status :: 4 - Beta
Classifier: Intended Audience :: Developers
Classifier: Natural Language :: English
Classifier: Programming Language :: Python :: 3.7
Classifier: Programming Language :: Python :: 3.8
Classifier: Programming Language :: Python :: 3.9
Classifier: Programming Language :: Python :: 3.10
Classifier: License :: OSI Approved :: Apache Software License
Requires-Python: >=3.7
License-File: LICENSE
Requires-Dist: numpy
Provides-Extra: dev
